Metadata-Version: 2.4
Name: Scan_binpy
Version: 0.0.1
Summary: Scan_binpy original programming
Author: R00T.bin
Author-email: pedromarsan06@gmail.com
License: MIT License
Keywords: Scan_binpy
License-File: LICENCE
Dynamic: author
Dynamic: author-email
Dynamic: description
Dynamic: description-content-type
Dynamic: keywords
Dynamic: license
Dynamic: license-file
Dynamic: summary
